docknet/__init__.py
docknet/_about.py
docknet/_cli.py
docknet/config.py
docknet/main.py
docknet/api/__init__.py
docknet/api/api.py
docknet/api/dependencies.py
docknet/api/error_handling.py
docknet/api/endpoints/__init__.py
docknet/api/endpoints/auth.py
docknet/api/endpoints/deployment.py
docknet/api/endpoints/extension.py
docknet/api/endpoints/file.py
docknet/api/endpoints/json_db.py
docknet/api/endpoints/project.py
docknet/api/endpoints/seed.py
docknet/api/endpoints/system.py
docknet/api/endpoints/user.py
docknet/api/endpoints/templates/register-admin-success.html.j2
docknet/api/endpoints/templates/register-admin.html.j2
docknet/clients/__init__.py
docknet/clients/auth.py
docknet/clients/components.py
docknet/clients/deployment.py
docknet/clients/extension.py
docknet/clients/file.py
docknet/clients/json_db.py
docknet/clients/project.py
docknet/clients/shared.py
docknet/clients/system.py
docknet/managers/__init__.py
docknet/managers/auth.py
docknet/managers/components.py
docknet/managers/extension.py
docknet/managers/project.py
docknet/managers/seed.py
docknet/managers/system.py
docknet/managers/deployment/__init__.py
docknet/managers/deployment/docker.py
docknet/managers/deployment/docker_utils.py
docknet/managers/deployment/kube_utils.py
docknet/managers/deployment/kubernetes.py
docknet/managers/deployment/manager.py
docknet/managers/deployment/utils.py
docknet/managers/file/__init__.py
docknet/managers/file/azure_blob.py
docknet/managers/file/minio.py
docknet/managers/json_db/__init__.py
docknet/managers/json_db/inmemory_dict.py
docknet/managers/json_db/postgres.py
docknet/operations/__init__.py
docknet/operations/auth.py
docknet/operations/components.py
docknet/operations/deployment.py
docknet/operations/extension.py
docknet/operations/file.py
docknet/operations/json_db.py
docknet/operations/project.py
docknet/operations/seed.py
docknet/operations/system.py
docknet/schema/__init__.py
docknet/schema/auth.py
docknet/schema/deployment.py
docknet-0.0.23.dist-info/LICENSE
docknet-0.0.23.dist-info/METADATA
docknet-0.0.23.dist-info/WHEEL
docknet-0.0.23.dist-info/entry_points.txt
docknet-0.0.23.dist-info/top_level.txt
docknet-0.0.23.dist-info/RECORD
